pkaani/__init__.py
pkaani/__main__.py
pkaani/ani_descriptors.py
pkaani/ase_io_proteindatabank_mod.py
pkaani/pkaani.py
pkaani/prep_pdb.py
pkaani/run.py
pkaani/models/ASP_ani2x_FINAL_MODEL_F100.joblib
pkaani/models/FASP.joblib
pkaani/models/FGLU.joblib
pkaani/models/FHIS.joblib
pkaani/models/FLYS.joblib
pkaani/models/FTYR.joblib
pkaani/models/GLU_ani2x_FINAL_MODEL_F75.joblib
pkaani/models/HIS_ani2x_FINAL_MODEL_F100.joblib
pkaani/models/LYS_ani2x_FINAL_MODEL_F25.joblib
pkaani/models/TYR_ani2x_FINAL_MODEL_F25.joblib
pkaani-0.1.10.dist-info/licenses/LICENSE
pkaani-0.1.10.dist-info/METADATA
pkaani-0.1.10.dist-info/WHEEL
pkaani-0.1.10.dist-info/entry_points.txt
pkaani-0.1.10.dist-info/top_level.txt
pkaani-0.1.10.dist-info/RECORD
