Metadata-Version: 2.4
Name: pkaani
Version: 0.1.10
Summary: A Python package to calculate pKa values for proteins
Home-page: https://github.com/isayevlab/pKa-ANI
Download-URL: https://github.com/isayevlab/pKa-ANI
Author: Hatice GOKCAN, Olexandr ISAYEV
Author-email: olexandr@olexandrisayev.com
Requires-Python: >=3.10
License-File: LICENSE
Requires-Dist: numpy
Requires-Dist: scipy
Requires-Dist: torch
Requires-Dist: torchani
Requires-Dist: scikit-learn==1.6.1
Requires-Dist: ase
Requires-Dist: joblib
Requires-Dist: setuptools
Dynamic: author
Dynamic: author-email
Dynamic: description
Dynamic: description-content-type
Dynamic: download-url
Dynamic: home-page
Dynamic: license-file
Dynamic: requires-dist
Dynamic: requires-python
Dynamic: summary
